{
  "list": [
    {
      "createdAt": "5/17/2020, 11:47:08 PM",
      "updatedAt": "5/17/2020, 11:47:08 PM",
      "name": "create component 2",
      "description": "Lorem ipsum dolor sit amet, consectetur adipisicing elit.",
      "id": 1,
      "editedAt": "5/18/2020, 1:01:57 AM"
    },
    {
      "createdAt": "5/17/2020, 11:48:10 PM",
      "updatedAt": "5/17/2020, 11:48:10 PM",
      "name": "run hooks asd asda das dsad asd",
      "description": "Lorem ipsum dolor sit amet, consectetur adipisicing elit.",
      "id": 3,
      "editedAt": "5/18/2020, 1:02:10 AM"
    },
    {
      "createdAt": "5/17/2020, 11:48:10 PM",
      "updatedAt": "5/17/2020, 11:48:10 PM",
      "name": "wash flower",
      "description": "Lorem ipsum dolor sit amet, consectetur adipisicing elit.",
      "id": 4
    },
    {
      "createdAt": "5/17/2020, 11:48:10 PM",
      "updatedAt": "5/17/2020, 11:48:10 PM",
      "name": "walk with dog",
      "description": "Lorem ipsum dolor sit amet, consectetur adipisicing elit.",
      "id": 5
    },
    {
      "createdAt": "5/17/2020, 11:48:10 PM",
      "updatedAt": "5/17/2020, 11:48:10 PM",
      "name": "run",
      "description": "Lorem ipsum dolor sit amet, consectetur adipisicing elit.",
      "id": 6
    },
    {
      "createdAt": "5/17/2020, 11:48:10 PM",
      "updatedAt": "5/17/2020, 11:48:10 PM",
      "name": "wash dishes",
      "description": "dsadsad",
      "id": 7,
      "editedAt": "5/18/2020, 1:02:24 AM"
    },
    {
      "createdAt": "5/18/2020, 12:48:16 AM",
      "updatedAt": "5/18/2020, 12:48:16 AM",
      "name": "dsd",
      "description": "dasdasd",
      "id": 8
    }
  ]
}